iconostasis/__init__.py
iconostasis/__main__.py
iconostasis/iconostasis.py
iconostasis-0.0.2.dist-info/LICENSE
iconostasis-0.0.2.dist-info/METADATA
iconostasis-0.0.2.dist-info/WHEEL
iconostasis-0.0.2.dist-info/entry_points.txt
iconostasis-0.0.2.dist-info/top_level.txt
iconostasis-0.0.2.dist-info/RECORD
